import_policies/__init__.py
import_policies/contracts.py
python_import_policies-1.0.0.dist-info/LICENSE.md
python_import_policies-1.0.0.dist-info/METADATA
python_import_policies-1.0.0.dist-info/WHEEL
python_import_policies-1.0.0.dist-info/RECORD
