Metadata-Version: 2.1
Name: python-import-policies
Version: 1.0.0
Summary: Import Policies
Home-page: https://gitlab.com/sombrahq/python-libs/python-import-policies
License: MIT
Keywords: python,import,policy
Author: Yunier Rojas
Author-email: yunier@sombra.cc
Maintainer: Yunier Rojas García
Maintainer-email: yunier.rojas@gmail.com
Requires-Python: >=3.9,<4.0
Classifier: Development Status :: 3 - Alpha
Classifier: Intended Audience :: Developers
Classifier: License :: OSI Approved :: MIT License
Classifier: Programming Language :: Python :: 3
Classifier: Programming Language :: Python :: 3.9
Classifier: Programming Language :: Python :: 3.10
Classifier: Programming Language :: Python :: 3.11
Classifier: Programming Language :: Python :: 3.12
Requires-Dist: import-linter (>=1.12.1,<2.0.0)
Project-URL: Repository, https://gitlab.com/sombrahq/python-libs/python-import-policies
